binary_tree/__init__.py
binary_tree/binary_tree.py
binary_tree/heap_sort.py
binary_tree/heapify.py
binary_tree/priority_queue.py
tests/__init__.py
tests/test_bt_algorithms.py
tests/test_bt_attributes.py
tests/test_priority_queues.py
binary_tree_logicatcore-0.0.6.dist-info/LICENSE
binary_tree_logicatcore-0.0.6.dist-info/METADATA
binary_tree_logicatcore-0.0.6.dist-info/WHEEL
binary_tree_logicatcore-0.0.6.dist-info/top_level.txt
binary_tree_logicatcore-0.0.6.dist-info/RECORD
