Metadata-Version: 2.1
Name: binary-tree-logicatcore
Version: 0.0.6
Summary: Package comprising of binary tree data structure and its relevant algorithms
Home-page: https://github.com/logicatcore/binary_tree
Author: Sai Sharath
Author-email: kakubalsai@gmail.com
License: UNKNOWN
Platform: UNKNOWN
Classifier: Programming Language :: Python :: 3
Classifier: License :: OSI Approved :: MIT License
Classifier: Operating System :: OS Independent
Requires-Python: >=3.8
